img2cmplx/__init__.py
img2cmplx/io.py
img2cmplx/simplify.py
img2cmplx-0.0.4.dist-info/LICENSE
img2cmplx-0.0.4.dist-info/METADATA
img2cmplx-0.0.4.dist-info/WHEEL
img2cmplx-0.0.4.dist-info/top_level.txt
img2cmplx-0.0.4.dist-info/RECORD
