Metadata-Version: 2.1
Name: img2cmplx
Version: 0.0.4
Summary: Extract a simplicial complex from a raster
Home-page: UNKNOWN
Author: David L. Millman
Author-email: <dave@cs.unc.edu>
License: UNKNOWN
Keywords: python,TDA
Platform: UNKNOWN
Classifier: Development Status :: 3 - Alpha
Classifier: Intended Audience :: Education
Classifier: Programming Language :: Python :: 3
Classifier: Operating System :: MacOS :: MacOS X
Classifier: Operating System :: Microsoft :: Windows
Classifier: Operating System :: POSIX :: Linux
Requires-Dist: Pillow
Requires-Dist: opencv-python
Requires-Dist: networkx
Requires-Dist: numpy
Requires-Dist: scipy
